leetconfig/__init__.py
leetconfig/entry.py
leetconfig/entry_converter.py
leetconfig/group.py
leetconfig/namespace.py
leetconfig/parser.py
leetconfig/py.typed
leetconfig/recursive_entry_converter.py
leetconfig/definitions/__init__.py
leetconfig/definitions/authentication.py
leetconfig/definitions/logger.py
leetconfig/definitions/logger_struct.py
leetconfig/definitions/server.py
leetconfig/definitions/server_client.py
leetconfig/definitions/ssh.py
leetconfig/definitions/telnet.py
leetconfig/format/__init__.py
leetconfig/format/abstract_format.py
leetconfig/format/cli.py
leetconfig/format/cli_null.py
leetconfig/format/cli_subcommand.py
leetconfig/format/dictionary.py
leetconfig/format/environment.py
leetconfig/format/file_yaml.py
leetconfig-0.0.1.dist-info/LICENSE
leetconfig-0.0.1.dist-info/METADATA
leetconfig-0.0.1.dist-info/WHEEL
leetconfig-0.0.1.dist-info/top_level.txt
leetconfig-0.0.1.dist-info/RECORD
