Metadata-Version: 2.1
Name: leetconfig
Version: 0.0.1
Summary: Reusable configuration definition for a Python application.
Home-page: https://gitlab.com/redballoonsecurity/leetconfig
Author: Red Balloon Security
License: UNKNOWN
Project-URL: Bug Tracker, https://gitlab.com/redballoonsecurity/leetconfig/-/issues
Platform: UNKNOWN
Classifier: Intended Audience :: Developers
Classifier: License :: OSI Approved :: MIT License
Classifier: Natural Language :: English
Classifier: Topic :: Software Development
Requires-Python: >=3.7, <=3.8
License-File: LICENSE
Requires-Dist: pyyaml (==5.4)
Requires-Dist: structlog (~=20.1.0)
Requires-Dist: enum34 ; python_version < "3.4"
Provides-Extra: test
Requires-Dist: pytest ; extra == 'test'
Requires-Dist: pytest-cov ; extra == 'test'
Requires-Dist: mypy ; (python_version >= "3.5") and extra == 'test'
Requires-Dist: types-PyYAML (==5.4) ; (python_version >= "3.5") and extra == 'test'
